nixpass/__init__.py
nixpass/__main__.py
nixpass/nixpass.py
nixpass-2.0.dist-info/LICENSE
nixpass-2.0.dist-info/METADATA
nixpass-2.0.dist-info/WHEEL
nixpass-2.0.dist-info/entry_points.txt
nixpass-2.0.dist-info/top_level.txt
nixpass-2.0.dist-info/RECORD
