Metadata-Version: 2.1
Name: nixpass
Version: 2.0
Summary: A cli password management tool
Home-page: https://github.com/gatovato/nixpass
Author: Shane Guymon
Author-email: shane.eguymon@gmail.com
License: UNKNOWN
Platform: UNKNOWN
Classifier: Programming Language :: Python :: 3
Classifier: License :: OSI Approved :: MIT License
Classifier: Operating System :: POSIX :: Linux
Classifier: Topic :: Terminals
Requires-Python: >=3
Requires-Dist: pycrypto
